timeql/__init__.py
timeql-0.0.0.dev0.dist-info/LICENSE.txt
timeql-0.0.0.dev0.dist-info/METADATA
timeql-0.0.0.dev0.dist-info/WHEEL
timeql-0.0.0.dev0.dist-info/entry_points.txt
timeql-0.0.0.dev0.dist-info/top_level.txt
timeql-0.0.0.dev0.dist-info/RECORD
