Metadata-Version: 2.1
Name: timeql
Version: 0.0.0.dev0
Summary: TimeQL programming language implemented in python
Home-page: https://github.com/timeql/timeql
Author: 3demax
Author-email: contact@timeql.org
License: UNKNOWN
Project-URL: Bug Reports, https://github.com/timeql/timeql/issues
Project-URL: Say Thanks!, https://saythanks.io/to/3demax
Keywords: timeql language interpreter development
Platform: UNKNOWN
Classifier: Development Status :: 1 - Planning
Classifier: Intended Audience :: Developers
Classifier: Topic :: Software Development :: Interpreters
Classifier: License :: OSI Approved :: MIT License
Classifier: Programming Language :: Python :: 3
Classifier: Programming Language :: Python :: 3.4
Classifier: Programming Language :: Python :: 3.5
Classifier: Programming Language :: Python :: 3.6
Classifier: Programming Language :: Python :: 3.7
Requires-Python: >=3.5, <4
